beyonddefer/BL/InDefense.py
beyonddefer/BL/__init__.py
beyonddefer/BL/compare_confidence_cost.py
beyonddefer/BL/lce_cost.py
beyonddefer/BL/one_v_all_cost.py
beyonddefer/Datasets/__init__.py
beyonddefer/Datasets/cifar.py
beyonddefer/Experiments/CIFAR10K.py
beyonddefer/Experiments/SampleComp.py
beyonddefer/Experiments/__init__.py
beyonddefer/Experiments/acc_vs_c.py
beyonddefer/Experiments/basic.py
beyonddefer/Experiments/basic_parallel.py
beyonddefer/Experiments/comparison.py
beyonddefer/Experiments/cost_sensitive_cov_acc.py
beyonddefer/Experiments/no_loss_acc_cov.py
beyonddefer/Feature_Acquisition/__init__.py
beyonddefer/Feature_Acquisition/active.py
beyonddefer/Fig-Operations/fig.py
beyonddefer/Fig-Operations/run_this.sh
beyonddefer/MyMethod/CompareConfAdd.py
beyonddefer/MyMethod/CompareConfMeta.py
beyonddefer/MyMethod/CompareConfMetaCost.py
beyonddefer/MyMethod/__init__.py
beyonddefer/MyMethod/additional_cost.py
beyonddefer/MyMethod/additional_defer.py
beyonddefer/MyMethod/beyond_defer.py
beyonddefer/MyMethod/cost_sensitive.py
beyonddefer/MyMethod/learned_additional.py
beyonddefer/MyMethod/learned_beyond.py
beyonddefer/MyNet/__init__.py
beyonddefer/MyNet/call_net.py
beyonddefer/MyNet/networks.py
beyonddefer/Tests/__init__.py
beyonddefer/Tests/mini_test.py
beyonddefer/Tests/test.py
beyonddefer/__init__.py
beyonddefer/__main__.py
beyonddefer/human_ai_defer/.git
beyonddefer/human_ai_defer/.gitignore
beyonddefer/human_ai_defer/README.md
beyonddefer/human_ai_defer/__init__.py
beyonddefer/human_ai_defer/baselines/__init__.py
beyonddefer/human_ai_defer/baselines/basemethod.py
beyonddefer/human_ai_defer/baselines/compare_confidence.py
beyonddefer/human_ai_defer/baselines/differentiable_triage.py
beyonddefer/human_ai_defer/baselines/lce_surrogate.py
beyonddefer/human_ai_defer/baselines/mix_of_exps.py
beyonddefer/human_ai_defer/baselines/one_v_all.py
beyonddefer/human_ai_defer/baselines/selective_prediction.py
beyonddefer/human_ai_defer/datasets.PNG
beyonddefer-1.0.7.dist-info/METADATA
beyonddefer-1.0.7.dist-info/WHEEL
beyonddefer-1.0.7.dist-info/RECORD
