Metadata-Version: 2.1
Name: beyonddefer
Version: 1.0.7
Summary: The code for paper 'Is Learn to Defer Enough? Optimal Predictors that Incorporate Human Decisions'
Author: BeyondDefer Authors
Requires-Python: >=3.8
Classifier: Programming Language :: Python :: 3
Classifier: Programming Language :: Python :: 3.8
Classifier: Programming Language :: Python :: 3.9
Classifier: Programming Language :: Python :: 3.10
Classifier: Programming Language :: Python :: 3.11
Classifier: Programming Language :: Python :: 3.12
Requires-Dist: Pillow (>=10.1.0,<11.0.0)
Requires-Dist: matplotlib (==3.6.*)
Requires-Dist: numpy (>=1.24.4,<2.0.0)
Requires-Dist: osfclient (>=0.0.5,<0.0.6)
Requires-Dist: pandas (>=2.0.3,<3.0.0)
Requires-Dist: requests (>=2.31.0,<3.0.0)
Requires-Dist: scikit-learn (>=1.3.2,<2.0.0)
Requires-Dist: scipy (>=1.10.1,<2.0.0)
Requires-Dist: sentence-transformers (>=2.2.2,<3.0.0)
Requires-Dist: tikzplotlib (>=0.10.1,<0.11.0)
Requires-Dist: torch (>=2.1.1,<3.0.0)
Requires-Dist: torchtext (>=0.16.1,<0.17.0)
Requires-Dist: torchvision (>=0.16.1,<0.17.0)
Requires-Dist: tqdm (>=4.66.1,<5.0.0)
